gwo_package/__init__.py
gwo_package-0.1.0.dist-info/licenses/LICENSE
gwo_package-0.1.0.dist-info/METADATA
gwo_package-0.1.0.dist-info/WHEEL
gwo_package-0.1.0.dist-info/top_level.txt
gwo_package-0.1.0.dist-info/RECORD
