Metadata-Version: 2.4
Name: gwo-package
Version: 0.1.0
Summary: A Grey Wolf Optimizer (GWO) algorithm implemented in Python
Author-email: Your Name <you@example.com>
License-Expression: MIT
Project-URL: Homepage, https://github.com/yourusername/opengreywolfoptimizer
Requires-Python: >=3.7
License-File: LICENSE
Dynamic: license-file
